[
  {
    "name": "theme_info",
    "theme_name": "Custom Theme",
    "theme_version": "1.0.0",
    "theme_author": "Cardinal & Co. Agency",
    "theme_documentation_url": "https:\/\/cardinalco.agency\/",
    "theme_support_url": "https:\/\/cardinalco.agency\/"
  },
  {
    "name": "Global",
    "settings": [
      {
        "type": "header",
        "content": "Logo"
      },
      {
        "type": "html",
        "id": "logo_svg",
        "label": "SVG"
      },
      {
       "type": "image_picker",
       "id": "logo_image",
       "label": "PNG"
      },
      {
        "type": "header",
        "content": "Secondary Logo"
      },
      {
        "type": "html",
        "id": "secondary_logo",
        "label": "SVG"
      },
      {
        "type": "url",
        "id": "shop_all_link",
        "label": "Shop All Link"
      },
      {
        "type": "header",
        "content": "Custom Inquiry Link"
      },
      {
        "type": "text",
        "id": "custom_inquiry_label",
        "label": "Label",
        "default": "Custom Inquiry"
      },
      {
          "type": "url",
          "id": "custom_inquiry_link",
          "label": "Link"
      }
    ]
  },
  {
    "name": "Cart",
    "settings": [
      {
        "type": "checkbox",
        "id": "enable_shipping_bar",
        "label": "Enable Shipping Bar"
      }
    ]
  },
  {
    "name": "t:settings_schema.social-media.name",
    "settings": [
      {
        "type": "header",
        "content": "t:settings_schema.social-media.settings.header.content"
      },
      {
        "type": "text",
        "id": "social_twitter_link",
        "label": "t:settings_schema.social-media.settings.social_twitter_link.label",
        "info": "t:settings_schema.social-media.settings.social_twitter_link.info"
      },
      {
        "type": "text",
        "id": "social_facebook_link",
        "label": "t:settings_schema.social-media.settings.social_facebook_link.label",
        "info": "t:settings_schema.social-media.settings.social_facebook_link.info"
      },
      {
        "type": "text",
        "id": "social_pinterest_link",
        "label": "t:settings_schema.social-media.settings.social_pinterest_link.label",
        "info": "t:settings_schema.social-media.settings.social_pinterest_link.info"
      },
      {
        "type": "text",
        "id": "social_instagram_link",
        "label": "t:settings_schema.social-media.settings.social_instagram_link.label",
        "info": "t:settings_schema.social-media.settings.social_instagram_link.info"
      },
      {
        "type": "text",
        "id": "social_tiktok_link",
        "label": "t:settings_schema.social-media.settings.social_tiktok_link.label",
        "info": "t:settings_schema.social-media.settings.social_tiktok_link.info"
      },
      {
        "type": "text",
        "id": "social_tumblr_link",
        "label": "t:settings_schema.social-media.settings.social_tumblr_link.label",
        "info": "t:settings_schema.social-media.settings.social_tumblr_link.info"
      },
      {
        "type": "text",
        "id": "social_snapchat_link",
        "label": "t:settings_schema.social-media.settings.social_snapchat_link.label",
        "info": "t:settings_schema.social-media.settings.social_snapchat_link.info"
      },
      {
        "type": "text",
        "id": "social_youtube_link",
        "label": "t:settings_schema.social-media.settings.social_youtube_link.label",
        "info": "t:settings_schema.social-media.settings.social_youtube_link.info"
      },
      {
        "type": "text",
        "id": "social_vimeo_link",
        "label": "t:settings_schema.social-media.settings.social_vimeo_link.label",
        "info": "t:settings_schema.social-media.settings.social_vimeo_link.info"
      }
    ]
  },
  {
    "name": "t:settings_schema.favicon.name",
    "settings": [
      {
        "type": "image_picker",
        "id": "favicon",
        "label": "t:settings_schema.favicon.settings.favicon.label",
        "info": "t:settings_schema.favicon.settings.favicon.info"
      }
    ]
  }
]